qsctl-1.7.0-py2.7-nspkg.pth
qingstor/qsctl/__init__.py
qingstor/qsctl/__init__.pyc
qingstor/qsctl/compat.py
qingstor/qsctl/compat.pyc
qingstor/qsctl/constants.py
qingstor/qsctl/driver.py
qingstor/qsctl/utils.py
qingstor/qsctl/__pycache__/__init__.cpython-34.pyc
qingstor/qsctl/__pycache__/__init__.cpython-35.pyc
qingstor/qsctl/__pycache__/compat.cpython-34.pyc
qingstor/qsctl/__pycache__/compat.cpython-35.pyc
qingstor/qsctl/__pycache__/constants.cpython-35.pyc
qingstor/qsctl/__pycache__/utils.cpython-35.pyc
qingstor/qsctl/commands/__init__.py
qingstor/qsctl/commands/base.py
qingstor/qsctl/commands/cp.py
qingstor/qsctl/commands/ls.py
qingstor/qsctl/commands/mb.py
qingstor/qsctl/commands/mv.py
qingstor/qsctl/commands/presign.py
qingstor/qsctl/commands/rb.py
qingstor/qsctl/commands/rm.py
qingstor/qsctl/commands/sync.py
qingstor/qsctl/commands/transfer.py
qingstor/qsctl/helper/__init__.py
qingstor/qsctl/helper/qsdocutils.py
qingstor/qsctl/helper/textwriter.py
qingstor/qsctl/helper/source/qsctl-cp.rst
qingstor/qsctl/helper/source/qsctl-ls.rst
qingstor/qsctl/helper/source/qsctl-mb.rst
qingstor/qsctl/helper/source/qsctl-mv.rst
qingstor/qsctl/helper/source/qsctl-presign.rst
qingstor/qsctl/helper/source/qsctl-rb.rst
qingstor/qsctl/helper/source/qsctl-rm.rst
qingstor/qsctl/helper/source/qsctl-sync.rst
qingstor/qsctl/helper/source/qsctl.rst
qsctl-1.7.0.data/scripts/qsctl
qsctl-1.7.0.data/scripts/qsctl.cmd
qsctl-1.7.0.dist-info/DESCRIPTION.rst
qsctl-1.7.0.dist-info/METADATA
qsctl-1.7.0.dist-info/RECORD
qsctl-1.7.0.dist-info/WHEEL
qsctl-1.7.0.dist-info/metadata.json
qsctl-1.7.0.dist-info/namespace_packages.txt
qsctl-1.7.0.dist-info/top_level.txt
tests/__init__.py
tests/test_utils.py
