Metadata-Version: 2.0
Name: qsctl
Version: 1.7.0
Summary: Advanced command line tool for QingStor.
Home-page: https://www.qingstor.com
Author: QingStor Dev Team
Author-email: qs-devel@yunify.com
License: UNKNOWN
Keywords: yunify qingcloud qingstor qsctl object_storage
Platform: UNKNOWN
Requires-Dist: PyYAML (>=3.1)
Requires-Dist: docutils (>=0.10)
Requires-Dist: futures
Requires-Dist: qingstor-sdk (>=2.1.3)
Requires-Dist: tqdm (>=4.0.0)
